gfxhat/__init__.py
gfxhat/st7567.py
gfxhat/lcd.py
gfxhat/backlight.py
gfxhat/touch.py
gfxhat/fonts/__init__.py
gfxhat/fonts/OFL.txt
gfxhat/fonts/Bitbuntu.bdf
gfxhat/fonts/AmaticSC-Bold.ttf
gfxhat/fonts/bitbuntu-license.txt
gfxhat/fonts/Bitocra-Full.bdf
gfxhat/fonts/AmaticSC-Regular.ttf
gfxhat/fonts/FredokaOne-Regular.ttf
gfxhat/fonts/Bitbuntu-Full.bdf
gfxhat/fonts/Bitocra-13-Full.bdf
gfxhat/fonts/PressStart2P-Regular.ttf
gfxhat-0.0.1.dist-info/metadata.json
gfxhat-0.0.1.dist-info/WHEEL
gfxhat-0.0.1.dist-info/METADATA
gfxhat-0.0.1.dist-info/DESCRIPTION.rst
gfxhat-0.0.1.dist-info/top_level.txt
gfxhat-0.0.1.dist-info/RECORD
